{"width":1333,"height":2000,"ApplicationRecordVersion":"\u0000\u0004","ObjectName":"GT2 RS","DateCreated":"20200228","TimeCreated":"144605-0600","DigitalCreationDate":"20200228","DigitalCreationTime":"144605-0600","Byline":"Erik S Olsen","Caption":"A white 993 GT2 RS at South Bay Porsche.","Make":"SONY","Model":"ILCE-7M3","ExposureTime":0.025,"FNumber":2,"ISO":100,"DateTimeOriginal":"2020-02-28T20:46:05.000Z","ShutterSpeedValue":5.321928,"ApertureValue":2,"FocalLength":40,"WhiteBalance":"Auto","LensModel":"ZEISS Batis 2/40 CF"}